bingai/__init__.py
bingai/edge.py
bingai/main.py
bingai-1.1.1.dist-info/LICENSE
bingai-1.1.1.dist-info/METADATA
bingai-1.1.1.dist-info/WHEEL
bingai-1.1.1.dist-info/top_level.txt
bingai-1.1.1.dist-info/RECORD
