Metadata-Version: 2.1
Name: bingai
Version: 1.1.1
Summary: Bing API for ChatGPT
Author-email: Gautam Veldanda <gautamveldanda@gmail.com>
Project-URL: Homepage, https://github.com/gautamveldanda/bingai
Classifier: Programming Language :: Python :: 3
Classifier: License :: OSI Approved :: MIT License
Classifier: Operating System :: OS Independent
Requires-Python: >=3.7
License-File: LICENSE
Requires-Dist: selenium
